zoho_analytics_connector/analytics_client_upstream.py
zoho_analytics_connector/enhanced_report_client.py
zoho_analytics_connector/report_client.py
zoho_analytics_connector/typed_dicts.py
zoho_analytics_connector-1.5.1.dist-info/LICENSE
zoho_analytics_connector-1.5.1.dist-info/METADATA
zoho_analytics_connector-1.5.1.dist-info/WHEEL
zoho_analytics_connector-1.5.1.dist-info/top_level.txt
zoho_analytics_connector-1.5.1.dist-info/RECORD
