Metadata-Version: 2.2
Name: zoho_analytics_connector
Version: 1.5.1
Summary: Zoho Analytics connector
Home-page: https://github.com/timrichardson/zoho_analytics_connector
Author: Tim Richardson
Author-email: tim@growthpath.com.au
License: MPL-2.0
Keywords: zoho analytics
Classifier: Development Status :: 5 - Production/Stable
Classifier: License :: OSI Approved :: MIT License
Classifier: Programming Language :: Python :: 3.9
Classifier: Programming Language :: Python :: 3.10
Classifier: Programming Language :: Python :: 3.11
Classifier: Programming Language :: Python :: 3.12
Classifier: Topic :: Office/Business
Requires-Python: >=3.9
License-File: LICENSE
Requires-Dist: requests
Requires-Dist: emoji
Dynamic: author
Dynamic: author-email
Dynamic: classifier
Dynamic: description
Dynamic: description-content-type
Dynamic: home-page
Dynamic: keywords
Dynamic: license
Dynamic: requires-dist
Dynamic: requires-python
Dynamic: summary
